{
  "last_updated": "2026-05-05",
  "park": {
    "name": "北京环球度假区",
    "name_en": "Universal Studios Beijing",
    "location": "北京市通州区",
    "opening_time": "09:00",
    "closing_time": {
      "weekday": "20:00",
      "weekend_holiday": "21:00",
      "note": "实际闭园时间因季节和活动而异，以官方App为准"
    },
    "entry_deadline": {
      "weekday": "19:00",
      "weekend_holiday": "20:00",
      "note": "停止入园时间，非闭园时间"
    },
    "zones": [
      "哈利波特区",
      "小黄人区",
      "侏罗纪区",
      "变形金刚区",
      "功夫熊猫区",
      "水世界",
      "好莱坞",
      "城市大道"
    ]
  },
  "version": "3.2.0",
  "source_files": [
    {
      "id": "src_img_01",
      "filename": "微信图片_20260406153535_286_3.jpg",
      "type": "image",
      "description": "年卡攻略：淡季、人流量判断、餐饮"
    },
    {
      "id": "src_img_02",
      "filename": "微信图片_20260406153536_287_3.jpg",
      "type": "image",
      "description": "拍照服务+游玩策略"
    },
    {
      "id": "src_img_03",
      "filename": "微信图片_20260406153537_288_3.jpg",
      "type": "image",
      "description": "日票建议+演出对比+隐藏技巧"
    },
    {
      "id": "src_img_04",
      "filename": "微信图片_20260406153538_289_3.jpg",
      "type": "image",
      "description": "备忘录1：哈利波特+小黄人评价"
    },
    {
      "id": "src_img_05",
      "filename": "微信图片_20260406153539_290_3.jpg",
      "type": "image",
      "description": "备忘录2：侏罗纪+变形金刚评价"
    },
    {
      "id": "src_img_06",
      "filename": "微信图片_20260406153539_291_3.jpg",
      "type": "image",
      "description": "备忘录3：功夫熊猫+项目排名总结"
    },
    {
      "id": "src_img_07",
      "filename": "微信图片_20260406153540_292_3.jpg",
      "type": "image",
      "description": "行程安排(上午+中午)"
    },
    {
      "id": "src_img_08",
      "filename": "微信图片_20260406153541_293_3.jpg",
      "type": "image",
      "description": "行程安排(下午+傍晚)"
    },
    {
      "id": "src_img_09",
      "filename": "微信图片_20260406153542_294_3.jpg",
      "type": "image",
      "description": "行程安排(傍晚+演出时间)"
    },
    {
      "id": "src_txt_01",
      "filename": "新建 文本文档.txt",
      "type": "text",
      "description": "排队技巧"
    },
    {
      "id": "src_txt_02",
      "filename": "新建 文本文档 - 副本.txt",
      "type": "text",
      "description": "交通+小道+忠告+错峰时间"
    },
    {
      "id": "src_txt_03",
      "filename": "新建 文本文档 - 副本 (2).txt",
      "type": "text",
      "description": "存包指引+行前准备"
    },
    {
      "id": "src_xhs_01",
      "filename": "小红书截图_美食测评.jpg",
      "type": "image",
      "description": "小红书攻略截图：9家餐厅评价+餐饮避雷+排名讨论"
    },
    {
      "id": "src_xhs_02",
      "filename": "小红书截图_行前准备.jpg",
      "type": "image",
      "description": "小红书攻略截图：安检禁忌+必带物品+错峰时段+游玩秘籍"
    },
    {
      "id": "src_txt_04",
      "type": "text",
      "filename": "新建 文本文档.txt",
      "description": "打车指南、演出推荐、雪泥指南"
    },
    {
      "id": "md_00",
      "filename": "src/00_总索引.md",
      "category": "index",
      "type": "compiled"
    },
    {
      "id": "md_01",
      "filename": "src/01_行前准备/行前准备.md",
      "category": "preparation",
      "type": "compiled"
    },
    {
      "id": "md_02",
      "filename": "src/02_入园策略/入园策略.md",
      "category": "entry_strategy",
      "type": "compiled"
    },
    {
      "id": "md_03",
      "filename": "src/03_园区导航/秘密小道.md",
      "category": "navigation",
      "type": "compiled"
    },
    {
      "id": "md_04a",
      "filename": "src/04_项目攻略/哈利波特园区.md",
      "category": "attraction_guide",
      "type": "compiled"
    },
    {
      "id": "md_04b",
      "filename": "src/04_项目攻略/小黄人园区.md",
      "category": "attraction_guide",
      "type": "compiled"
    },
    {
      "id": "md_04c",
      "filename": "src/04_项目攻略/侏罗纪园区.md",
      "category": "attraction_guide",
      "type": "compiled"
    },
    {
      "id": "md_04d",
      "filename": "src/04_项目攻略/变形金刚园区.md",
      "category": "attraction_guide",
      "type": "compiled"
    },
    {
      "id": "md_04e",
      "filename": "src/04_项目攻略/功夫熊猫园区.md",
      "category": "attraction_guide",
      "type": "compiled"
    },
    {
      "id": "md_04f",
      "filename": "src/04_项目攻略/水世界及其他.md",
      "category": "attraction_guide",
      "type": "compiled"
    },
    {
      "id": "md_04g",
      "filename": "src/04_项目攻略/项目总评与排名.md",
      "category": "attraction_guide",
      "type": "compiled"
    },
    {
      "id": "md_05",
      "filename": "src/05_餐饮美食/餐饮美食.md",
      "category": "dining",
      "type": "compiled"
    },
    {
      "id": "md_06",
      "filename": "src/06_演出时间/演出时间表.md",
      "category": "show_schedule",
      "type": "compiled"
    },
    {
      "id": "md_07",
      "filename": "src/07_行程安排/一日游行程.md",
      "category": "itinerary",
      "type": "compiled"
    },
    {
      "id": "md_08",
      "filename": "src/08_隐藏技巧/隐藏技巧.md",
      "category": "tips",
      "type": "compiled"
    },
    {
      "id": "md_09",
      "filename": "src/09_避雷提醒/避雷提醒.md",
      "category": "warnings",
      "type": "compiled"
    },
    {
      "id": "md_xhs_01",
      "filename": "src/10_小红书补充/餐饮与项目补充.md",
      "category": "supplementary",
      "type": "compiled"
    },
    {
      "id": "md_xhs_02",
      "filename": "src/10_小红书补充/行前与技巧补充.md",
      "category": "supplementary",
      "type": "compiled"
    }
  ],
  "schema_version": "3.2.0",
  "previous_version": "2.0.0",
  "migration_date": "2026-04-08",
  "changes": [
    "zone_id → zone_ids (全实体统一为数组)",
    "taste_tags → tags (dishes 统一)",
    "warn_warn_* ID 规范化为 warn_{category}_{编号}",
    "删除 6 条重复 warning",
    "修正 9 条餐饮 warning 的 zone 标签",
    "关联孤儿 warning 到对应实体",
    "express_pass 价格类型统一为 object",
    "restaurants 新增 warning_ids",
    "preparations 新增 warning_ids"
  ]
}